objdictgen/__init__.py
objdictgen/__main__.py
objdictgen/config/DS-302.prf
objdictgen/config/DS-401.prf
objdictgen/config/DS-402.prf
objdictgen/config/DS-404.prf
objdictgen/config/DS-406.prf
objdictgen/config/DS-408.prf
objdictgen/config/DS-410.prf
objdictgen/config/DS-418.prf
objdictgen/config/DS-419.prf
objdictgen/eds_utils.py
objdictgen/gen_cfile.py
objdictgen/img/networkedit.ico
objdictgen/img/networkedit.png
objdictgen/jsonod.py
objdictgen/maps.py
objdictgen/node.py
objdictgen/nodelist.py
objdictgen/nodemanager.py
objdictgen/nosis.py
objdictgen/printing.py
objdictgen/py.typed
objdictgen/schema/od.schema.json
objdictgen/typing.py
objdictgen/ui/__init__.py
objdictgen/ui/commondialogs.py
objdictgen/ui/exception.py
objdictgen/ui/networkedit.py
objdictgen/ui/networkeditortemplate.py
objdictgen/ui/nodeeditortemplate.py
objdictgen/ui/objdictedit.py
objdictgen/ui/subindextable.py
objdictgen/utils.py
objdictgen-3.5.4.dist-info/WHEEL
objdictgen-3.5.4.dist-info/entry_points.txt
objdictgen-3.5.4.dist-info/METADATA
objdictgen-3.5.4.dist-info/RECORD
