Metadata-Version: 2.4
Name: objdictgen
Version: 3.5.4
Summary: CanFestival Object Dictionary tool
Author: Svein Seldal
Author-email: Svein Seldal <sveinse@laerdal.com>
License-Expression: LGPL-2.1-or-later
Classifier: Development Status :: 4 - Beta
Classifier: Intended Audience :: Developers
Classifier: Topic :: Software Development :: Build Tools
Classifier: Topic :: Software Development :: Code Generators
Classifier: Topic :: Software Development :: Embedded Systems
Classifier: Topic :: Software Development :: Libraries :: Application Frameworks
Classifier: License :: OSI Approved :: GNU Lesser General Public License v2 or later (LGPLv2+)
Classifier: Programming Language :: Python :: 3
Classifier: Programming Language :: Python :: 3.10
Classifier: Programming Language :: Python :: 3.11
Classifier: Programming Language :: Python :: 3.12
Classifier: Programming Language :: Python :: 3 :: Only
Requires-Dist: jsonschema
Requires-Dist: colorama
Requires-Dist: deepdiff
Requires-Dist: ruff ; extra == 'dev'
Requires-Dist: mypy ; extra == 'dev'
Requires-Dist: types-setuptools ; extra == 'dev'
Requires-Dist: types-colorama ; extra == 'dev'
Requires-Dist: types-wxpython ; extra == 'dev'
Requires-Dist: pytest ; extra == 'dev'
Requires-Dist: coverage ; extra == 'dev'
Requires-Dist: pytest-cov ; extra == 'dev'
Requires-Dist: pytest-mock ; extra == 'dev'
Requires-Dist: freezegun ; extra == 'dev'
Requires-Dist: wxpython ; extra == 'ui'
Requires-Python: >=3.10, <4
Project-URL: Bug Tracker, https://github.com/Laerdal/python-objdictgen/issues
Project-URL: Repository, https://github.com/Laerdal/python-objdictgen
Provides-Extra: dev
Provides-Extra: ui
